geode_hybrid/__init__.py
geode_hybrid/__init__.pyi
geode_hybrid/brep.py
geode_hybrid/brep.pyi
geode_hybrid/py.typed
geode_hybrid/lib64/__init__.pyi
geode_hybrid/lib64/geode_hybrid_py_brep.cpython-311-x86_64-linux-gnu.so
geode_hybrid/lib64/geode_hybrid_py_brep.pyi
geode_hybrid/lib64/libGeode-Hybrid_brep.so
geode_hybrid-3.3.0.dist-info/METADATA
geode_hybrid-3.3.0.dist-info/WHEEL
geode_hybrid-3.3.0.dist-info/top_level.txt
geode_hybrid-3.3.0.dist-info/RECORD
