Metadata-Version: 2.4
Name: Geode-Hybrid
Version: 3.3.0
Summary: Hybrid remeshing Geode-solutions OpenGeode module
Author-email: Geode-solutions <contact@geode-solutions.com>
License: Proprietary
Requires-Python: <3.13,>=3.9
Requires-Dist: geode-background==9.*,>=9.9.0
Requires-Dist: geode-common==33.*,>=33.15.0
Requires-Dist: geode-numerics==6.*,>=6.4.9
Requires-Dist: geode-simplex==9.*,>=9.9.0
Requires-Dist: opengeode-core==15.*,>=15.30.11
Requires-Dist: opengeode-inspector==6.*,>=6.8.12
